uiautomator2cache/__init__.py
uiautomator2cache/__version__.py
uiautomator2cache/cache/app-uiautomator-test.apk-652bf9e13c/app-uiautomator-test.apk
uiautomator2cache/cache/app-uiautomator.apk-d3f17174fb/app-uiautomator.apk
uiautomator2cache/cache/atx-agent_0.10.0_linux_386.tar.gz-1f8cdf3239/atx-agent_0.10.0_linux_386.tar.gz
uiautomator2cache/cache/atx-agent_0.10.0_linux_arm64.tar.gz-a5e23d45ed/atx-agent_0.10.0_linux_arm64.tar.gz
uiautomator2cache/cache/atx-agent_0.10.0_linux_armv7.tar.gz-cf3333ae7b/atx-agent_0.10.0_linux_armv7.tar.gz
uiautomator2cache/cache/minicap-3d0b86b17d/minicap
uiautomator2cache/cache/minicap-4ad740a772/minicap
uiautomator2cache/cache/minicap-7386d7f362/minicap
uiautomator2cache/cache/minicap-c1e34d7ae0/minicap
uiautomator2cache/cache/minicap.so-010087d6d0/minicap.so
uiautomator2cache/cache/minicap.so-031700ed26/minicap.so
uiautomator2cache/cache/minicap.so-0684edc7d5/minicap.so
uiautomator2cache/cache/minicap.so-0750876ce8/minicap.so
uiautomator2cache/cache/minicap.so-14ea849b4c/minicap.so
uiautomator2cache/cache/minicap.so-15ef6f04e2/minicap.so
uiautomator2cache/cache/minicap.so-19de789fdd/minicap.so
uiautomator2cache/cache/minicap.so-2d140e498d/minicap.so
uiautomator2cache/cache/minicap.so-3520fb4f63/minicap.so
uiautomator2cache/cache/minicap.so-36aac77a10/minicap.so
uiautomator2cache/cache/minicap.so-3869b17ab4/minicap.so
uiautomator2cache/cache/minicap.so-394284d042/minicap.so
uiautomator2cache/cache/minicap.so-4006d15d46/minicap.so
uiautomator2cache/cache/minicap.so-43a2a93f13/minicap.so
uiautomator2cache/cache/minicap.so-4973801f87/minicap.so
uiautomator2cache/cache/minicap.so-52e9e445e7/minicap.so
uiautomator2cache/cache/minicap.so-589faa364e/minicap.so
uiautomator2cache/cache/minicap.so-626f19b279/minicap.so
uiautomator2cache/cache/minicap.so-64dc02c031/minicap.so
uiautomator2cache/cache/minicap.so-664df8acbf/minicap.so
uiautomator2cache/cache/minicap.so-71bfec4d95/minicap.so
uiautomator2cache/cache/minicap.so-7af1a3b8f5/minicap.so
uiautomator2cache-0.3.1.dist-info/LICENSE
uiautomator2cache-0.3.1.dist-info/METADATA
uiautomator2cache-0.3.1.dist-info/WHEEL
uiautomator2cache-0.3.1.dist-info/top_level.txt
uiautomator2cache-0.3.1.dist-info/RECORD
