Metadata-Version: 2.1
Name: uiautomator2cache
Version: 0.3.1
Summary: uiautomator2 assets cache
Home-page: https://github.com/LmeSzinc/uiautomator2cache
Author: LmeSzinc
Author-email: lmeszincsales@gamil.com
License: UNKNOWN
Platform: python3
Classifier: Programming Language :: Python :: 3
Requires-Python: >=3.7
